web_image_generate/__init__.py
web_image_generate/blocks.py
web_image_generate/image_generator.py
web_image_generate/example/textToImage.yaml
chatgpt_mirai_qq_bot_web_image_generate-0.3.4.dist-info/LICENSE
chatgpt_mirai_qq_bot_web_image_generate-0.3.4.dist-info/METADATA
chatgpt_mirai_qq_bot_web_image_generate-0.3.4.dist-info/WHEEL
chatgpt_mirai_qq_bot_web_image_generate-0.3.4.dist-info/entry_points.txt
chatgpt_mirai_qq_bot_web_image_generate-0.3.4.dist-info/top_level.txt
chatgpt_mirai_qq_bot_web_image_generate-0.3.4.dist-info/RECORD
