Metadata-Version: 2.1
Name: chatgpt-mirai-qq-bot-web-image-generate
Version: 0.3.4
Summary: WebImageGeneratePlugin for lss233/chatgpt-mirai-qq-bot
Home-page: https://github.com/chuanSir123/web_image_generate
Author: chuanSir
Author-email: 416448943@qq.com
Project-URL: Bug Tracker, https://github.com/chuanSir123/web_image_generate/issues
Project-URL: Documentation, https://github.com/chuanSir123/web_image_generate/wiki
Project-URL: Source Code, https://github.com/chuanSir123/web_image_generate
Classifier: Programming Language :: Python :: 3
Classifier: License :: OSI Approved :: GNU Affero General Public License v3
Classifier: Operating System :: OS Independent
Requires-Python: >=3.8
License-File: LICENSE
Requires-Dist: kirara-ai>=3.2.0
Requires-Dist: gradio-client
